aiautocommit/__init__.py
aiautocommit/difftastic.py
aiautocommit/internet.py
aiautocommit/prepare-commit-msg
aiautocommit/prompt/commit_prompt.txt
aiautocommit/prompt/commit_suffix.txt
aiautocommit/prompt/excluded_files.txt
aiautocommit/prompt/examples/example_1.md
aiautocommit/prompt/examples/example_2.md
aiautocommit/prompt/examples/example_3.md
aiautocommit-0.14.0.dist-info/METADATA
aiautocommit-0.14.0.dist-info/WHEEL
aiautocommit-0.14.0.dist-info/entry_points.txt
aiautocommit-0.14.0.dist-info/licenses/LICENSE
aiautocommit-0.14.0.dist-info/RECORD
