Metadata-Version: 2.4
Name: aiautocommit
Version: 0.14.0
Summary: AI generated commit messages
Project-URL: Repository, https://github.com/iloveitaly/aiautocommit
Author-email: Michael Bianco <mike@mikebian.co>
License-File: LICENSE
Keywords: ai,automation,commit,git,openai
Requires-Python: >=3.8
Requires-Dist: backoff>=2.2.1
Requires-Dist: click>=8.1.7
Requires-Dist: openai>=1.54.3
